{
  "entryId" : "edu.only4.danmuku.adapter.portal.api.web.UCenterInteractController::getDanmukuPage",
  "entryType" : "controllermethod",
  "nodeCount" : 3,
  "edgeCount" : 2,
  "nodes" : [ {
    "id" : "edu.only4.danmuku.adapter.application.queries.video_danmuku.GetVideoDanmukuPageQryHandler",
    "name" : "GetVideoDanmukuPageQryHandler",
    "fullName" : "edu.only4.danmuku.adapter.application.queries.video_danmuku.GetVideoDanmukuPageQryHandler",
    "type" : "queryhandler"
  }, {
    "id" : "edu.only4.danmuku.adapter.portal.api.web.UCenterInteractController::getDanmukuPage",
    "name" : "UCenterInteractController::getDanmukuPage",
    "fullName" : "edu.only4.danmuku.adapter.portal.api.web.UCenterInteractController::getDanmukuPage",
    "type" : "controllermethod"
  }, {
    "id" : "edu.only4.danmuku.application.queries.video_danmuku.GetVideoDanmukuPageQry.Request",
    "name" : "GetVideoDanmukuPageQry.Request",
    "fullName" : "edu.only4.danmuku.application.queries.video_danmuku.GetVideoDanmukuPageQry.Request",
    "type" : "query"
  } ],
  "edges" : [ {
    "fromId" : "edu.only4.danmuku.adapter.portal.api.web.UCenterInteractController::getDanmukuPage",
    "toId" : "edu.only4.danmuku.application.queries.video_danmuku.GetVideoDanmukuPageQry.Request",
    "type" : "ControllerMethodToQuery",
    "label" : null
  }, {
    "fromId" : "edu.only4.danmuku.application.queries.video_danmuku.GetVideoDanmukuPageQry.Request",
    "toId" : "edu.only4.danmuku.adapter.application.queries.video_danmuku.GetVideoDanmukuPageQryHandler",
    "type" : "QueryToQueryHandler",
    "label" : null
  } ]
}